README.md
setup.py
Time2Feat/Time2Feat.py
Time2Feat/__init__.py
Time2Feat.egg-info/PKG-INFO
Time2Feat.egg-info/SOURCES.txt
Time2Feat.egg-info/dependency_links.txt
Time2Feat.egg-info/requires.txt
Time2Feat.egg-info/top_level.txt
Time2Feat.egg-info/zip-safe
Time2Feat/checkpoint/__init__.py
Time2Feat/data/__init__.py
Time2Feat/data/dataset.py
Time2Feat/data/reader.py
Time2Feat/extraction/__init__.py
Time2Feat/extraction/extractor.py
Time2Feat/extraction/extractor_pair.py
Time2Feat/extraction/extractor_single.py
Time2Feat/model/__init__.py
Time2Feat/model/clustering.py
Time2Feat/model/preprocessing.py
Time2Feat/ranking/__init__.py
Time2Feat/ranking/algorithms.py
Time2Feat/ranking/baseline.py
Time2Feat/ranking/ensemble.py
Time2Feat/ranking/wrapper.py
Time2Feat/selection/PFA.py
Time2Feat/selection/__init__.py
Time2Feat/selection/search.py
Time2Feat/selection/selection.py
Time2Feat/utils/__init__.py
Time2Feat/utils/importance_old.py